README.md
license.txt
setup.cfg
setup.py
AuthAlpha/Non_Password_Hashing.py
AuthAlpha/OTPMethods.py
AuthAlpha/Password_Hashing.py
AuthAlpha/__init__.py
authalpha.egg-info/PKG-INFO
authalpha.egg-info/SOURCES.txt
authalpha.egg-info/dependency_links.txt
authalpha.egg-info/top_level.txt