Metadata-Version: 2.1
Name: authalpha
Version: 0.9.0a0
Summary: A python abstraction to generate and authenticate hashes of passwords and files of any type. The package can also be used to implement classic and Time Based OTPs.
Home-page: https://github.com/Theorist-Git/AuthAlpha
Author: Mayank Vats
Author-email: dev-theorist.e5xna@simplelogin.com
License: GNU GPLv3
Download-URL: https://github.com/Theorist-Git/AuthAlpha/archive/refs/tags/v0.9.0-alpha.tar.gz
Keywords: AUTHENTICATION,CRYPTOGRAPHY,HASHING,TWO FACTOR AUTHENTICATION
Platform: UNKNOWN
Classifier: Development Status :: 3 - Alpha
Classifier: Intended Audience :: Developers
Classifier: Topic :: Software Development :: Build Tools
Classifier: License :: OSI Approved :: GNU General Public License v3 or later (GPLv3+)
Classifier: Programming Language :: Python :: 3
Classifier: Programming Language :: Python :: 3.4
Classifier: Programming Language :: Python :: 3.5
Classifier: Programming Language :: Python :: 3.6
Classifier: Programming Language :: Python :: 3.9
License-File: license.txt
